dj_admin_plus/__init__.py
dj_admin_plus/admin.py
dj_admin_plus/apps.py
dj_admin_plus/fields.py
dj_admin_plus/forms.py
dj_admin_plus/mixins.py
dj_admin_plus/models.py
dj_admin_plus/navigation.py
dj_admin_plus/tests.py
dj_admin_plus/urls.py
dj_admin_plus/utils.py
dj_admin_plus/views.py
dj_admin_plus/widgets.py
dj_admin_plus/static/dj-admin-plus/css/forms.css
dj_admin_plus/static/dj-admin-plus/css/style.css
dj_admin_plus/static/tinymce/js/tinymce/tinymce.min.js
dj_admin_plus/static/tinymce/js/tinymce/icons/default/icons.min.js
dj_admin_plus/static/tinymce/js/tinymce/models/dom/model.min.js
dj_admin_plus/static/tinymce/js/tinymce/plugins/accordion/plugin.min.js
dj_admin_plus/static/tinymce/js/tinymce/plugins/advlist/plugin.min.js
dj_admin_plus/static/tinymce/js/tinymce/plugins/anchor/plugin.min.js
dj_admin_plus/static/tinymce/js/tinymce/plugins/autolink/plugin.min.js
dj_admin_plus/static/tinymce/js/tinymce/plugins/autoresize/plugin.min.js
dj_admin_plus/static/tinymce/js/tinymce/plugins/autosave/plugin.min.js
dj_admin_plus/static/tinymce/js/tinymce/plugins/charmap/plugin.min.js
dj_admin_plus/static/tinymce/js/tinymce/plugins/code/plugin.min.js
dj_admin_plus/static/tinymce/js/tinymce/plugins/codesample/plugin.min.js
dj_admin_plus/static/tinymce/js/tinymce/plugins/directionality/plugin.min.js
dj_admin_plus/static/tinymce/js/tinymce/plugins/emoticons/plugin.min.js
dj_admin_plus/static/tinymce/js/tinymce/plugins/emoticons/js/emojiimages.js
dj_admin_plus/static/tinymce/js/tinymce/plugins/emoticons/js/emojiimages.min.js
dj_admin_plus/static/tinymce/js/tinymce/plugins/emoticons/js/emojis.js
dj_admin_plus/static/tinymce/js/tinymce/plugins/emoticons/js/emojis.min.js
dj_admin_plus/static/tinymce/js/tinymce/plugins/fullscreen/plugin.min.js
dj_admin_plus/static/tinymce/js/tinymce/plugins/help/plugin.min.js
dj_admin_plus/static/tinymce/js/tinymce/plugins/help/js/i18n/keynav/ar.js
dj_admin_plus/static/tinymce/js/tinymce/plugins/help/js/i18n/keynav/bg_BG.js
dj_admin_plus-0.0.2.dist-info/LICENSE
dj_admin_plus-0.0.2.dist-info/METADATA
dj_admin_plus-0.0.2.dist-info/WHEEL
dj_admin_plus-0.0.2.dist-info/top_level.txt
dj_admin_plus-0.0.2.dist-info/RECORD
