Metadata-Version: 2.1
Name: dj-admin-plus
Version: 0.0.2
Summary: DJ Admin plus is a pluggable easy to use modern admin for Django framework.
License: MIT
Classifier: Programming Language :: Python :: 3
Classifier: License :: OSI Approved :: MIT License
Classifier: Operating System :: OS Independent
Requires-Python: >=3.7
License-File: LICENSE
